splitsio/__init__.py
splitsio/api.py
splitsio/plot.py
splitsio/query.py
splitsio-0.1.1.dist-info/LICENSE
splitsio-0.1.1.dist-info/WHEEL
splitsio-0.1.1.dist-info/METADATA
splitsio-0.1.1.dist-info/RECORD
